{"SFRWYG": {"name": "Wonyoung", "rarity": "SS"}, "SFRMKA": {"name": "Moka", "rarity": "SS"}, "SFRKAI": {"name": "Kai", "rarity": "SS"}, "SFRAHI": {"name": "Asahi", "rarity": "SS"}, "SFRJGK": {"name": "Jungkook", "rarity": "SS"}, "SFRRMM": {"name": "RM", "rarity": "SS"}, "SFRYGN": {"name": "Younghoon", "rarity": "SS"}, "SFRNNA": {"name": "Nana", "rarity": "SS"}, "SFRKMN": {"name": "Kamden", "rarity": "SS"}, "SFRIMM": {"name": "I.M", "rarity": "SS"}, "SFRDNO": {"name": "Dino", "rarity": "SS"}, "SFRYYN": {"name": "Yooyeon", "rarity": "SS"}, "SFRBAN": {"name": "Bain", "rarity": "SS"}, "SFRWOZ": {"name": "Woodz", "rarity": "SS"}, "SFRCEY": {"name": "Choerry", "rarity": "SS"}, "SFRTKI": {"name": "Taki", "rarity": "SS"}, "SFRQCY": {"name": "Quackity", "rarity": "SS"}, "SFRTEN": {"name": "Ten", "rarity": "SS"}, "SFRRRY": {"name": "Rhea Ripley", "rarity": "SS"}, "SFRBMN": {"name": "Beomhan", "rarity": "SS"}}